setup.py
brynq_sdk_trimergo/__init__.py
brynq_sdk_trimergo/timesheet.py
brynq_sdk_trimergo.egg-info/PKG-INFO
brynq_sdk_trimergo.egg-info/SOURCES.txt
brynq_sdk_trimergo.egg-info/dependency_links.txt
brynq_sdk_trimergo.egg-info/not-zip-safe
brynq_sdk_trimergo.egg-info/requires.txt
brynq_sdk_trimergo.egg-info/top_level.txt
brynq_sdk_trimergo/pageinfo_wrapper/__init__.py
brynq_sdk_trimergo/pageinfo_wrapper/pageinfo.py
brynq_sdk_trimergo/schemas/__init__.py
brynq_sdk_trimergo/schemas/timesheet.py