Metadata-Version: 1.0
Name: brynq-sdk-trimergo
Version: 1.0.0
Summary: Trimergo wrapper from BrynQ
Home-page: UNKNOWN
Author: BrynQ
Author-email: support@brynq.com
License: BrynQ License
Platform: UNKNOWN
